provisionpad/__init__.py
provisionpad/aws/__init__.py
provisionpad/aws/aws_ec2.py
provisionpad/aws/aws_iam.py
provisionpad/aws/aws_sg.py
provisionpad/aws/aws_sts.py
provisionpad/aws/aws_vol.py
provisionpad/bin/__init__.py
provisionpad/bin/propad.py
provisionpad/db/__init__.py
provisionpad/db/database.py
provisionpad/helpers/__init__.py
provisionpad/helpers/namehelpers.py
provisionpad/helpers/texthelpers.py
provisionpad/helpers/update_status.py
provisionpad/runs/__init__.py
provisionpad/runs/attach_volume.py
provisionpad/runs/create_instance.py
provisionpad/runs/create_vpc.py
provisionpad/runs/initiate.py
provisionpad/runs/start_instance.py
provisionpad/runs/status.py
provisionpad/runs/stop_instance.py
provisionpad/runs/terminate_instance.py
provisionpad/runs/scripts/__init__.py
provisionpad/runs/scripts/tclock.py
provisionpad-0.0.3.dist-info/LICENSE
provisionpad-0.0.3.dist-info/METADATA
provisionpad-0.0.3.dist-info/WHEEL
provisionpad-0.0.3.dist-info/entry_points.txt
provisionpad-0.0.3.dist-info/top_level.txt
provisionpad-0.0.3.dist-info/RECORD
